{
	"name": "drag",
	"plugin-id": "Sprite",
	"sid": 403994236222908,
	"isGlobal": false,
	"instanceVariables": [
		{
			"name": "PosX",
			"type": "number",
			"desc": "",
			"show": true,
			"sid": 942969304385318
		},
		{
			"name": "PosY",
			"type": "number",
			"desc": "",
			"show": true,
			"sid": 412040036392173
		}
	],
	"behaviorTypes": [
		{
			"behaviorId": "Tween",
			"name": "Tween",
			"sid": 973236368911723
		},
		{
			"behaviorId": "DragnDrop",
			"name": "DragDrop",
			"sid": 500374812772984
		}
	],
	"effectTypes": [],
	"animations": {
		"items": [
			{
				"frames": [
					{
						"width": 6589,
						"height": 3935,
						"originX": 0.5,
						"originY": 0.5,
						"originalSource": "",
						"exportFormat": "lossless",
						"exportQuality": 0.8,
						"fileType": "image/png",
						"imageSpriteId": 800682,
						"useCollisionPoly": true,
						"duration": 1,
						"tag": ""
					},
					{
						"width": 6703,
						"height": 4273,
						"originX": 0.5,
						"originY": 0.5,
						"originalSource": "",
						"exportFormat": "lossless",
						"exportQuality": 0.8,
						"fileType": "image/png",
						"imageSpriteId": 1276141,
						"useCollisionPoly": true,
						"duration": 1,
						"tag": ""
					},
					{
						"width": 4723,
						"height": 8185,
						"originX": 0.5,
						"originY": 0.5,
						"originalSource": "",
						"exportFormat": "lossless",
						"exportQuality": 0.8,
						"fileType": "image/png",
						"imageSpriteId": 7624632,
						"useCollisionPoly": true,
						"duration": 1,
						"tag": ""
					}
				],
				"sid": 268748282080873,
				"name": "Default",
				"isLooping": false,
				"isPingPong": false,
				"repeatCount": 1,
				"repeatTo": 0,
				"speed": 0
			}
		],
		"subfolders": []
	}
}